{
    "code": "LLS 100",
    "name": "Intro Latina/Latino Studies",
    "credit_hour": "Credit:3 hours.",
    "criterias": [
        "Cultural Studies - US Minority",
        "Social & Beh Sci - Soc Sci"
    ],
    "sections": [
        {
            "status": "<span class=\"hide\">1</span><span class=\"sr-only\">1. section open</span><img src=\"/static/images/sectionOpen.png\" title=\"Open\" alt=\"Open\"/>",
            "favorite": "<a href=\"/login/refresh?r=/schedule/2024/spring/LLS/100\" data-toggle=\"popover\" data-trigger=\"hover\" data-content=\"Add this Section to a personalized favorites list.  Must be logged in.\"><span class=\"glyphicon glyphicon-star-empty app-font16 aria-label=Activate to add to favorites. \"></span> </a>",
            "crn": "36897",
            "type": "<div class=\"app-meeting\">Discussion/ Recitation</div>",
            "section": "<div class=\"app-meeting\">AD1</div>",
            "time": "<span class=\"hide\">1400</span><div class=\"app-meeting\">02:00PM - 02:50PM</div>",
            "day": "<div class=\"app-meeting\">R      </div>",
            "location": "<div class=\"app-meeting\">103 1207 W Oregon</div>",
            "instructor": "<div class=\"app-meeting\">Alvarez, L<br />Flores, N<br /></div>",
            "availability": "Open",
            "credit": null,
            "sectionTitle": null,
            "sectionDescription": null,
            "courseDescription": null,
            "sectionDegreeNotes": null,
            "courseDegreeNotes": "Social & Beh Sci - Soc Sci, and Cultural Studies - US Minority course.",
            "specialApproval": "",
            "approvalCode": null,
            "sectionFee": "",
            "sectionDateRange": "Meets 01/16/24-05/01/24",
            "partOfTerm": "1",
            "info": null,
            "corequest": null,
            "restricted": ""
        },
        {
            "status": "<span class=\"hide\">1</span><span class=\"sr-only\">1. section open</span><img src=\"/static/images/sectionOpen.png\" title=\"Open\" alt=\"Open\"/>",
            "favorite": "<a href=\"/login/refresh?r=/schedule/2024/spring/LLS/100\" data-toggle=\"popover\" data-trigger=\"hover\" data-content=\"Add this Section to a personalized favorites list.  Must be logged in.\"><span class=\"glyphicon glyphicon-star-empty app-font16 aria-label=Activate to add to favorites. \"></span> </a>",
            "crn": "36898",
            "type": "<div class=\"app-meeting\">Discussion/ Recitation</div>",
            "section": "<div class=\"app-meeting\">AD2</div>",
            "time": "<span class=\"hide\">1500</span><div class=\"app-meeting\">03:00PM - 03:50PM</div>",
            "day": "<div class=\"app-meeting\">R      </div>",
            "location": "<div class=\"app-meeting\">103 1207 W Oregon</div>",
            "instructor": "<div class=\"app-meeting\">Alvarez, L<br />Flores, N<br /></div>",
            "availability": "Open",
            "credit": null,
            "sectionTitle": null,
            "sectionDescription": null,
            "courseDescription": null,
            "sectionDegreeNotes": null,
            "courseDegreeNotes": "Social & Beh Sci - Soc Sci, and Cultural Studies - US Minority course.",
            "specialApproval": "",
            "approvalCode": null,
            "sectionFee": "",
            "sectionDateRange": "Meets 01/16/24-05/01/24",
            "partOfTerm": "1",
            "info": null,
            "corequest": null,
            "restricted": ""
        },
        {
            "status": "<span class=\"hide\">1</span><span class=\"sr-only\">1. section open</span><img src=\"/static/images/sectionOpen.png\" title=\"Open\" alt=\"Open\"/>",
            "favorite": "<a href=\"/login/refresh?r=/schedule/2024/spring/LLS/100\" data-toggle=\"popover\" data-trigger=\"hover\" data-content=\"Add this Section to a personalized favorites list.  Must be logged in.\"><span class=\"glyphicon glyphicon-star-empty app-font16 aria-label=Activate to add to favorites. \"></span> </a>",
            "crn": "36899",
            "type": "<div class=\"app-meeting\">Discussion/ Recitation</div>",
            "section": "<div class=\"app-meeting\">AD3</div>",
            "time": "<span class=\"hide\">1600</span><div class=\"app-meeting\">04:00PM - 04:50PM</div>",
            "day": "<div class=\"app-meeting\">R      </div>",
            "location": "<div class=\"app-meeting\">103 1207 W Oregon</div>",
            "instructor": "<div class=\"app-meeting\">Flores, N<br />Gaytan, L<br /></div>",
            "availability": "Open",
            "credit": null,
            "sectionTitle": null,
            "sectionDescription": null,
            "courseDescription": null,
            "sectionDegreeNotes": null,
            "courseDegreeNotes": "Social & Beh Sci - Soc Sci, and Cultural Studies - US Minority course.",
            "specialApproval": "",
            "approvalCode": null,
            "sectionFee": "",
            "sectionDateRange": "Meets 01/16/24-05/01/24",
            "partOfTerm": "1",
            "info": null,
            "corequest": null,
            "restricted": ""
        },
        {
            "status": "<span class=\"hide\">1</span><span class=\"sr-only\">1. section open</span><img src=\"/static/images/sectionOpen.png\" title=\"Open\" alt=\"Open\"/>",
            "favorite": "<a href=\"/login/refresh?r=/schedule/2024/spring/LLS/100\" data-toggle=\"popover\" data-trigger=\"hover\" data-content=\"Add this Section to a personalized favorites list.  Must be logged in.\"><span class=\"glyphicon glyphicon-star-empty app-font16 aria-label=Activate to add to favorites. \"></span> </a>",
            "crn": "36900",
            "type": "<div class=\"app-meeting\">Discussion/ Recitation</div>",
            "section": "<div class=\"app-meeting\">AD4</div>",
            "time": "<span class=\"hide\">1300</span><div class=\"app-meeting\">01:00PM - 01:50PM</div>",
            "day": "<div class=\"app-meeting\">F      </div>",
            "location": "<div class=\"app-meeting\">103 1207 W Oregon</div>",
            "instructor": "<div class=\"app-meeting\">Flores, N<br />Gaytan, L<br /></div>",
            "availability": "Open",
            "credit": null,
            "sectionTitle": null,
            "sectionDescription": null,
            "courseDescription": null,
            "sectionDegreeNotes": null,
            "courseDegreeNotes": "Social & Beh Sci - Soc Sci, and Cultural Studies - US Minority course.",
            "specialApproval": "",
            "approvalCode": null,
            "sectionFee": "",
            "sectionDateRange": "Meets 01/16/24-05/01/24",
            "partOfTerm": "1",
            "info": null,
            "corequest": null,
            "restricted": ""
        },
        {
            "status": "<span class=\"hide\">1</span><span class=\"sr-only\">1. section open</span><img src=\"/static/images/sectionOpen.png\" title=\"Open\" alt=\"Open\"/>",
            "favorite": "<a href=\"/login/refresh?r=/schedule/2024/spring/LLS/100\" data-toggle=\"popover\" data-trigger=\"hover\" data-content=\"Add this Section to a personalized favorites list.  Must be logged in.\"><span class=\"glyphicon glyphicon-star-empty app-font16 aria-label=Activate to add to favorites. \"></span> </a>",
            "crn": "36901",
            "type": "<div class=\"app-meeting\">Lecture</div>",
            "section": "<div class=\"app-meeting\">AL1</div>",
            "time": "<span class=\"hide\">1300</span><div class=\"app-meeting\">01:00PM - 01:50PM</div>",
            "day": "<div class=\"app-meeting\">MW     </div>",
            "location": "<div class=\"app-meeting\">213 Gregory Hall</div>",
            "instructor": "<div class=\"app-meeting\">Flores, N<br /></div>",
            "availability": "Open",
            "credit": null,
            "sectionTitle": null,
            "sectionDescription": null,
            "courseDescription": null,
            "sectionDegreeNotes": null,
            "courseDegreeNotes": "Social & Beh Sci - Soc Sci, and Cultural Studies - US Minority course.",
            "specialApproval": "",
            "approvalCode": null,
            "sectionFee": "",
            "sectionDateRange": "Meets 01/16/24-05/01/24",
            "partOfTerm": "1",
            "info": null,
            "corequest": null,
            "restricted": ""
        }
    ]
}